{
  "id": "52211",
  "title": "Dragon Year Jigsaw",
  "slug": "dragon-year-jigsaw",
  "description": "Dive into the lively universe of Dragon Year Jigsaw, a comical online puzzle game set in the Chinese Dragon Year. Solve 24 levels of dragon-themed jigsaw puzzles, featuring vibrant and playful comic art. Perfect for puzzle lovers and those seeking a whimsical online experience. Join the fun &ndash; start piecing together your dragon adventure now!",
  "instructions": "Use your mouse or touch screen to drag and drop pieces into place Piece together whimsical dragon-themed images across 24 levels Its that simple ndash just drag drop and have fun unraveling the comical world of jigsaw puzzles ",
  "url": "https://html5.gamemonetize.com/yn3uwxmep3at3d7bjomh0je4gb21lewc/",
  "category": "Puzzle",
  "categorySlug": "puzzle",
  "tags": [
    "Arcade",
    "Jigsaw",
    "Puzzle"
  ],
  "thumb": "https://img.gamemonetize.com/yn3uwxmep3at3d7bjomh0je4gb21lewc/512x384.jpg",
  "width": 800,
  "height": 450,
  "publisher": "LofGames.com",
  "crawledAt": "2026-02-01T12:31:28.760Z"
}