{
  "id": "48760",
  "title": "Mr Bean Car Hidden Teddy Bear",
  "slug": "mr-bean-car-hidden-teddy-bear",
  "description": "Mr Bean Car Hidden Teddy Bear is a hidden game. Search all teddy bear within time limit between Mr. bean car.",
  "instructions": "mouse click or tap to play",
  "url": "https://html5.gamemonetize.com/6ozq4x43zec4dj5rkorsl41lemfw7fn4/",
  "category": "Puzzle",
  "categorySlug": "puzzle",
  "tags": [
    "Hidden"
  ],
  "thumb": "https://img.gamemonetize.com/6ozq4x43zec4dj5rkorsl41lemfw7fn4/512x384.jpg",
  "width": 800,
  "height": 600,
  "publisher": null,
  "crawledAt": "2026-02-01T22:22:40.783Z"
}