[
  1,
  [
    "a6epGRkuVBsLGilSh4huxH",
    "54gpCTbwlLDoX0e6I4uGsO",
    "d6wffNP8dIP5yARjJB6sDN",
    "0aDz4+C6dF7pgkWMZggAst",
    "930GlnSxpIIKDz8ZZfF/gf"
  ],
  [
    "_textureSetter"
  ],
  [
    "cc.SpriteFrame"
  ],
  0,
  [
    [
      [
        {
          "name": "IconSet",
          "rect": [
            0,
            0,
            89,
            93
          ],
          "offset": [
            0,
            0
          ],
          "originalSize": [
            89,
            93
          ],
          "capInsets": [
            0,
            0,
            0,
            0
          ]
        }
      ],
      [
        0
      ],
      0,
      [
        0
      ],
      [
        0
      ],
      [
        0
      ]
    ],
    [
      [
        {
          "name": "guang3",
          "rect": [
            0,
            0,
            252,
            239
          ],
          "offset": [
            0,
            0
          ],
          "originalSize": [
            252,
            239
          ],
          "capInsets": [
            0,
            0,
            0,
            0
          ]
        }
      ],
      [
        0
      ],
      0,
      [
        0
      ],
      [
        0
      ],
      [
        1
      ]
    ],
    [
      [
        {
          "name": "i_xingxing_953cf3cf-3cbd-45b2-bd9d-3309336fe819",
          "rect": [
            0,
            0,
            55,
            52
          ],
          "offset": [
            0,
            0
          ],
          "originalSize": [
            55,
            52
          ],
          "capInsets": [
            0,
            0,
            0,
            0
          ]
        }
      ],
      [
        0
      ],
      0,
      [
        0
      ],
      [
        0
      ],
      [
        2
      ]
    ],
    [
      [
        {
          "name": "20221202-140645",
          "rect": [
            44,
            39,
            175,
            180
          ],
          "offset": [
            3.5,
            -1
          ],
          "originalSize": [
            256,
            256
          ],
          "capInsets": [
            0,
            0,
            0,
            0
          ]
        }
      ],
      [
        0
      ],
      0,
      [
        0
      ],
      [
        0
      ],
      [
        3
      ]
    ],
    [
      [
        {
          "name": "sparkle_soft",
          "rect": [
            8,
            8,
            240,
            240
          ],
          "offset": [
            0,
            0
          ],
          "originalSize": [
            256,
            256
          ],
          "capInsets": [
            0,
            0,
            0,
            0
          ]
        }
      ],
      [
        0
      ],
      0,
      [
        0
      ],
      [
        0
      ],
      [
        4
      ]
    ]
  ]
]