{
  "id": "48713",
  "title": "GBox Memory",
  "slug": "gbox-memory",
  "description": "A game of the memory genre with a variety of modes. Search for pairs of identical tiles. Perfectly develops attention, memory, observation. Suitable for all ages, both children and adults. Game types: - Classic: Open the tiles on the board to find the same images, colors, or numbers. - Search: You need to find only the second tile to the displayed image or number. - Three of a kind: Find three identical tiles at once.",
  "instructions": "There is a field of tiles in front of you Remember their locations The players task is to open two identical tiles in succession A correctly opened pair disappears If two opened tiles in a row are different they are flipped back The game ends when a",
  "url": "https://html5.gamemonetize.com/dnu67txroir54wl0xo3lvtsyz8hskmpz/",
  "category": "Puzzle",
  "categorySlug": "puzzle",
  "tags": [
    "Best Games",
    "Brain",
    "Classic",
    "Matching",
    "Memory",
    "Mind",
    "Puzzle"
  ],
  "thumb": "https://img.gamemonetize.com/dnu67txroir54wl0xo3lvtsyz8hskmpz/512x384.jpg",
  "width": 800,
  "height": 600,
  "publisher": null,
  "crawledAt": "2026-02-01T19:21:32.963Z"
}