{
  "id": "54785",
  "title": "Wooden Bricks Vs Balls",
  "slug": "wooden-bricks-vs-balls",
  "description": "Wooden Bricks vs Balls is the ultimate brick-breaking challenge for all ages! Unleash the Ball-Blasting Frenzy in Wooden Bricks vs Balls! Prepare to shatter wooden blocks in this captivating brick-breaking adventure! Wooden Bricks vs Balls is a classic arcade game reinvented for modern audiences, offering endless fun and strategic challenges. Sharpen Your Aim and Demolish Wooden Structures: Master the art of aiming and unleash a barrage of balls to demolish intricate wooden structures in hundreds of unique levels. Each stage presents a fresh puzzle, demanding strategic thinking and precise shots to clear all blocks and progress.",
  "instructions": "Swipe your finger to aim the ball and Shoot and break wooden blocks with strategic shots ",
  "url": "https://html5.gamemonetize.com/en98nps66yop1z3pt5i81gad9ys3hw28/",
  "category": "Puzzle",
  "categorySlug": "puzzle",
  "tags": [
    "Ball",
    "Best Games",
    "Block",
    "Bricks",
    "Casual",
    "html5 games",
    "Hypercasual"
  ],
  "thumb": "https://img.gamemonetize.com/en98nps66yop1z3pt5i81gad9ys3hw28/512x384.jpg",
  "width": 640,
  "height": 1136,
  "publisher": null,
  "crawledAt": "2026-02-01T05:45:03.149Z"
}