{
  "id": "53199",
  "title": "Save The Hero   Pull The Pin",
  "slug": "save-the-hero-pull-the-pin",
  "description": "Get ready to fight with hero to save the treasure and princess. Pull pins and avoid traps to solve puzzles. You must pull the pins correctly from dragons, wolves and monsters to get the hidden treasure and reach the princess. Get ready for strategy without slowing down with 100 different levels in Save The Hero game!",
  "instructions": "Click and swipe with the mouse ",
  "url": "https://html5.gamemonetize.com/dhjb27kb8rjj7866ru6bk25zzfdb92yq/",
  "category": "Puzzle",
  "categorySlug": "puzzle",
  "tags": [
    "Action",
    "Brain",
    "Fantasy",
    "Kid",
    "Kids",
    "Mind",
    "Monster",
    "Princess",
    "Puzzle",
    "Strategy",
    "War"
  ],
  "thumb": "https://img.gamemonetize.com/dhjb27kb8rjj7866ru6bk25zzfdb92yq/512x384.jpg",
  "width": 800,
  "height": 600,
  "publisher": "MeyaGames",
  "crawledAt": "2026-02-01T10:38:51.639Z"
}